<DOMSymbolItem xmlns:xsi="http://www.w3.org/2001/XMLSchema-instance" xmlns="http://ns.adobe.com/xfl/2008/" name="skins/Perso1Skin_parts/head1" itemID="4ec2ed21-00000258" sourceLibraryItemHRef="Symbol 1" lastModified="1321397537">
  <timeline>
    <DOMTimeline name="head1">
      <layers>
        <DOMLayer name="Layer 1" color="#4FFF4F" current="true" isSelected="true">
          <frames>
            <DOMFrame index="0" keyMode="9728">
              <elements>
                <DOMGroup selected="true">
                  <members>
                    <DOMShape isDrawingObject="true">
                      <matrix>
                        <Matrix tx="-98.6"/>
                      </matrix>
                      <fills>
                        <FillStyle index="1">
                          <SolidColor color="#D0AA5A"/>
                        </FillStyle>
                      </fills>
                      <edges>
                        <Edge fillStyle1="1" edges="!3584 378[3621 469 3647 583!3647 583[3676 711 3668 776!3668 776[3660 841 3586 915!3586 915[3491 1010 3351 1029!3351 1029[3361 1206 3251 1336!3251 1336[3157 1446 2999 1498!2999 1498[2857 1546 2738 1526!2738 1526[2616 1506 2607 1429!2607
 1429[2602 1385 2581 1332!2581 1332[2568 1299 2536 1236!2536 1236[2495 1158 2437 1079!2437 1079[2190 747 2487 366!2487 366[2784 -16 3245 143!3245 143[3380 189 3455 237!3455 237[3552 297 3584 378"/>
                        <Edge cubics="!2487 366(;2685,111 2938,37 3245,143q2487 366Q2784 -16q3245 143);"/>
                        <Edge cubics="!3245 143(;3400,196 3537,261 3584,378q3245 143Q3380 189q3455 237Q3552 297q3584 378);"/>
                        <Edge cubics="!2536 1236(;2509,1184 2476,1132 2437,1079q2536 1236Q2495 1158q2437 1079);"/>
                        <Edge cubics="!2607 1429(;2600,1363 2569,1301 2536,1236q2607 1429Q2602 1385q2581 1332Q2568 1299q2536 1236);"/>
                        <Edge cubics="!2437 1079(;2272,858 2289,620 2487,366q2437 1079Q2190 747q2487 366);"/>
                        <Edge cubics="!3668 776(;3660,838 3562,1000 3351,1029q3668 776Q3660 841q3586 915Q3491 1010q3351 1029);"/>
                        <Edge cubics="!3351 1029(;3381,1538 2631,1638 2607,1429q3351 1029Q3361 1206q3251 1336Q3157 1446q2999 1498Q2857 1546q2738 1526Q2616 1506q2607 1429);"/>
                        <Edge cubics="!3668 776(;3680,683 3628,486 3584,378q3668 776Q3676 711q3647 583Q3621 469q3584 378);"/>
                      </edges>
                    </DOMShape>
                    <DOMShape isDrawingObject="true">
                      <matrix>
                        <Matrix tx="-98.6"/>
                      </matrix>
                      <fills>
                        <FillStyle index="1">
                          <SolidColor color="#D3B368"/>
                        </FillStyle>
                      </fills>
                      <edges>
                        <Edge fillStyle1="1" edges="
!3576 384[3613 472 3636 569!3636 569[3659 665 3659 735!3659 735[3648 885 3523 970!3523 970[3409 1047 3138 1108!3138 1108[3208 1026 3249 790!3249 790[3289 553 3559 360!3559 360[3575 383 3576 384"/>
                        <Edge cubics="!3559 360(;3567,371 3573,377 3576,384q3559 360Q3575 383q3576 384);"/>
                        <Edge cubics="!3576 384(;3626,502 3659,642 3659,735q3576 384Q3613 472q3636 569Q3659 665q3659 735);"/>
                        <Edge cubics="!3659 735(;3644,942 3485,1030 3138,1108q3659 735Q3648 885q3523 970Q3409 1047q3138 1108);"/>
                        <Edge cubics="!3559 360(;3379,489 3276,632 3249,790q3559 360Q3289 553q3249 790);"/>
                        <Edge cubics="!3249 790(;3222,947 3185,1053 3138,1108q3249 790Q3208 1026q3138 1108);"/>
                      </edges>
                    </DOMShape>
                    <DOMShape isDrawingObject="true">
                      <matrix>
                        <Matrix tx="-98.6"/>
                      </matrix>
                      <fills>
                        <FillStyle index="1">
                          <SolidColor color="#CDA14D"/>
                        </FillStyle>
                      </fills>
                      <edges>
                        <Edge fillStyle0="1" edges="
!3489 274[#D40.03 #C1.0F 3245 143!3245 143[2784 -16 2487 366!2487 366[2190 747 2437 1079!2437 1079[2495 1158 2536 1236!2536 1236[2568 1299 2581 1332!2581 1332[2602 1385 2607 1429!2607 1429[2616 1506 2738 1526!2738 1526[#AB9.0A #5F7.2F
 2752 1528!2752 1528[#ABA.0F #5E2.E1 2736.5 1478!2736.5 1478[#AA7.06 #5A9.25 2786 1261.5!2786 1261.5[#B1C.D2 #431.E2 2620 860.5!2620 860.5[#95B.4B #287.11 2701.5 363.5!2701.5 363.5[#BBF.D8 #4F.CD 3251 161!3251 161[#D4D.27 #D4.92 3489
 274"/>
                        <Edge cubics="!2487 366(;2685,111 2938,37 3245,143q2487 366Q2784 -16q3245 143);"/>
                        <Edge cubics="!3245 143(;3347,178 3430,223 3489,274q3245 143Q3392 193q3489 274);"/>
                        <Edge cubics="!2536 1236(;2509,1184 2476,1132 2437,1079q2536 1236Q2495 1158q2437 1079);"/>
                        <Edge cubics="!2607 1429(;2600,1363 2569,1301 2536,1236q2607 1429Q2602 1385q2581 1332Q2568 1299q2536 1236);"/>
                        <Edge cubics="!2437 1079(;2272,858 2289,620 2487,366q2437 1079Q2190 747q2487 366);"/>
                        <Edge cubics="!2752 1528(;2675,1520 2614,1486 2607,1429q2752 1528 2738 1526Q2616 1506q2607 1429);"/>
                        <Edge cubics="!3251 161(;3354,196 3433,233 3489,274q3251 161Q3405 213q3489 274);"/>
                        <Edge cubics="!2620 861(;2470,718 2497,553 2702,364q2620 861Q2395 647q2702 364);"/>
                        <Edge cubics="!2737 1478(;2730,1459 2747,1387 2786,1262q2737 1478Q2727 1449q2786 1262);"/>
                        <Edge cubics="!2752 1528(;2748,1514 2743,1497 2737,1478q2752 1528Q2746 1507q2737 1478);"/>
                        <Edge cubics="!2786 1262(;2825,1137 2770,1003 2620,861q2786 1262Q2845 1074q2620 861);"/>
                        <Edge cubics="!2702 364(;2906,175 3089,107 3251,161q2702 364Q3008 80q3251 161);"/>
                      </edges>
                    </DOMShape>
                  </members>
                </DOMGroup>
                <DOMGroup selected="true">
                  <members>
                    <DOMShape isDrawingObject="true">
                      <matrix>
                        <Matrix tx="-98.6"/>
                      </matrix>
                      <fills>
                        <FillStyle index="1">
                          <SolidColor color="#C49948"/>
                        </FillStyle>
                      </fills>
                      <edges>
                        <Edge fillStyle1="1" edges="
!2605 1733[2642 1582 2607 1429!2607 1429[2585 1333 2536 1236!2536 1236[#A98.A2 #377.82 2961 1007!2961 1007[#CB1.E #4D6.6A 3412 1717!3412 1717[3297 1747 3221 1880!3221 1880[3145 2014 3158 2167!3158 2167[3145 2251 3035 2292!3035 2292[2937
 2328 2799 2320!2799 2320[2665 2312 2568 2266!2568 2266[2463 2216 2457 2144!2457 2144[2512 2033 2548 1931!2548 1931[2578 1843 2605 1733"/>
                        <Edge cubics="!2607 1429(;2592,1365 2569,1301 2536,1236q2607 1429Q2585 1333q2536 1236);"/>
                        <Edge cubics="!2605 1733(;2630,1632 2630,1531 2607,1429q2605 1733Q2642 1582q2607 1429);"/>
                        <Edge cubics="!3158 2167(;3120,2404 2473,2346 2457,2144q3158 2167Q3145 2251q3035 2292Q2937 2328q2799 2320Q2665 2312q2568 2266Q2463 2216q2457 2144);"/>
                        <Edge cubics="!2457 2144(;2534,1987 2572,1869 2605,1733q2457 2144Q2512 2033q2548 1931Q2578 1843q2605 1733);"/>
                        <Edge cubics="!3412 1717(;3259,1757 3141,1962 3158,2167q3412 1717Q3297 1747q3221 1880Q3145 2014q3158 2167);"/>
                        <Edge cubics="!2536 1236(;2654,1004 2796,928 2961,1007q2536 1236Q2713 888q2961 1007);"/>
                        <Edge cubics="!2961 1007(;3154,1161 3304,1398 3412,1717q2961 1007Q3250 1238q3412 1717);"/>
                      </edges>
                    </DOMShape>
                    <DOMShape isDrawingObject="true">
                      <matrix>
                        <Matrix tx="-145.05" ty="-13.15"/>
                      </matrix>
                      <fills>
                        <FillStyle index="1">
                          <SolidColor color="#CDA14D"/>
                        </FillStyle>
                      </fills>
                      <edges>
                        <Edge fillStyle1="1" edges="
!3935 1976[#F4C.B8 #8E5.3D 4080 2013!4080 2013[#FFE.8D #8B6.CD 4016 2369!4016 2369[3875 2445.5 3804 2212!3804 2212[3761 2094 3804 1976!3804 1976[3998.5 1546 3935 1976"/>
                      </edges>
                    </DOMShape>
                  </members>
                </DOMGroup>
                <DOMGroup selected="true">
                  <members>
                    <DOMShape isDrawingObject="true">
                      <matrix>
                        <Matrix tx="-98.6"/>
                      </matrix>
                      <fills>
                        <FillStyle index="1">
                          <SolidColor color="#D3B368"/>
                        </FillStyle>
                      </fills>
                      <edges>
                        <Edge fillStyle0="1" edges="
!3665.5 727[#E51.2C #266.F8 3634 615!3634 615[#E12.D6 #267.0F 3368 745!3368 745[#C3D.0E #36A.FB 2967 1028!2967 1028[2963 1087 2963 1154!2963 1154[2964 1320 2996 1430!2996 1430[3034 1563 3165 1652!3165 1652[3223 1692 3275 1715!3275 1715
[3326 1737 3381 1749!3381 1749[3436 1761 3522 1752!3522 1752[#DE9.08 #6D3.FE 3604.5 1715!3604.5 1715[#E3F.EB #692.08 3651 1576!3651 1576[#E46.04 #5BD.F2 3656 1416.5!3656 1416.5[#E4A.23 #553.0A 3664.5 1291.5!3664.5 1291.5[#E56.8D #4C4.1F
 3636 1088!3636 1088[#E23.F6 #405.FA 3617.5 993.5!3617.5 993.5[#E1F.2 #3BD.0E 3640.5 898!3640.5 898[#E51.D1 #346.F6 3665.5 727"/>
                        <Edge cubics="!3522 1752(;3464,1758 3417,1757 3381,1749q3522 1752Q3436 1761q3381 1749);"/>
                        <Edge cubics="!3275 1715(;3240,1700 3204,1679 3165,1652q3275 1715Q3223 1692q3165 1652);"/>
                        <Edge cubics="!3381 1749(;3345,1741 3308,1730 3275,1715q3381 1749Q3326 1737q3275 1715);"/>
                        <Edge cubics="!3165 1652(;3079,1593 3022,1519 2996,1430q3165 1652Q3034 1563q2996 1430);"/>
                        <Edge cubics="!2996 1430(;2966,1327 2956,1169 2967,1028q2996 1430Q2964 1320q2963 1154 2967 1028);"/>
                        <Edge cubics="!3665 1292(;3669,1244 3659,1176 3636,1088q3665 1292Q3671 1220q3636 1088);"/>
                        <Edge cubics="!3656 1417(;3657,1381 3660,1339 3665,1292q3656 1417Q3658 1363q3665 1292);"/>
                        <Edge cubics="!3522 1752(;3548,1749 3576,1737 3605,1715q3522 1752Q3561 1748q3605 1715);"/>
                        <Edge cubics="!3605 1715(;3634,1693 3649,1647 3651,1576q3605 1715Q3648 1682q3651 1576);"/>
                        <Edge cubics="!3651 1576(;3653,1505 3655,1452 3656,1417q3651 1576Q3654 1470q3656 1417);"/>
                        <Edge cubics="!3641 898(;3658,859 3666,802 3666,727q3641 898Q3666 839q3666 727);"/>
                        <Edge cubics="!3634 615(;3613,615 3525,658 3368,745q3634 615Q3603 615q3368 745);"/>
                        <Edge cubics="!3666 727(;3665,652 3655,615 3634,615q3666 727Q3665 615q3634 615);"/>
                        <Edge cubics="!3636 1088(;3625,1049 3619,1018 3618,994q3636 1088Q3620 1030q3618 994);"/>
                        <Edge cubics="!3618 994(;3616,969 3624,937 3641,898q3618 994Q3615 957q3641 898);"/>
                        <Edge cubics="!3368 745(;3211,832 3078,926 2967,1028q3368 745Q3133 875q2967 1028);"/>
                      </edges>
                    </DOMShape>
                    <DOMShape isDrawingObject="true">
                      <matrix>
                        <Matrix tx="-98.6"/>
                      </matrix>
                      <fills>
                        <FillStyle index="1">
                          <SolidColor color="#D0AA5A"/>
                        </FillStyle>
                      </fills>
                      <edges>
                        <Edge fillStyle0="1" edges="
!3275.5 807.5[#BDE.EE #379.6C 2967 1028!2967 1028[2963 1087 2963 1154!2963 1154[2964 1320 2996 1430!2996 1430[3034 1563 3165 1652!3165 1652[3223 1692 3275 1715!3275 1715[3326 1737 3381 1749!3381 1749[3436 1761 3522 1752!3522 1752[#DE8.3
 #6D4.14 3602.5 1716.5!3602.5 1716.5[#DB6.58 #6C6.4 3475 1697!3475 1697[#D95.26 #66E.09 3276 1520!3276 1520[#C03.09 #571.F8 3239.5 1174.5!3239.5 1174.5[#D4B.AE #3BB.18 3484 1024!3484 1024[#DFF.B5 #381.49 3351 907!3351 907[#DB8.44 #2D5.B7
 3275.5 807.5"/>
                        <Edge cubics="!3522 1752(;3464,1758 3417,1757 3381,1749q3522 1752Q3436 1761q3381 1749);"/>
                        <Edge cubics="!3275 1715(;3240,1700 3204,1679 3165,1652q3275 1715Q3223 1692q3165 1652);"/>
                        <Edge cubics="!3381 1749(;3345,1741 3308,1730 3275,1715q3381 1749Q3326 1737q3275 1715);"/>
                        <Edge cubics="!3165 1652(;3079,1593 3022,1519 2996,1430q3165 1652Q3034 1563q2996 1430);"/>
                        <Edge cubics="!2996 1430(;2966,1327 2956,1169 2967,1028q2996 1430Q2964 1320q2963 1154 2967 1028);"/>
                        <Edge cubics="!3522 1752(;3547,1749 3574,1737 3603,1717q3522 1752Q3560 1748q3603 1717);"/>
                        <Edge cubics="!3351 907(;3458,786 3433,753 3276,808q3351 907Q3512 726q3276 808);"/>
                        <Edge cubics="!3475 1697(;3476,1663 3410,1604 3276,1520q3475 1697Q3477 1646q3276 1520);"/>
                        <Edge cubics="!3603 1717(;3541,1728 3498,1722 3475,1697q3603 1717Q3510 1734q3475 1697);"/>
                        <Edge cubics="!3484 1024(;3551,939 3506,900 3351,907q3484 1024Q3584 897q3351 907);"/>
                        <Edge cubics="!3276 808(;3118,862 3015,935 2967,1028q3276 808Q3039 889q2967 1028);"/>
                        <Edge cubics="!3240 1175(;3349,1028 3431,978 3484,1024q3240 1175Q3404 955q3484 1024);"/>
                        <Edge cubics="!3276 1520(;3142,1436 3130,1321 3240,1175q3276 1520Q3075 1394q3240 1175);"/>
                      </edges>
                    </DOMShape>
                    <DOMShape isDrawingObject="true">
                      <matrix>
                        <Matrix tx="-98.6"/>
                      </matrix>
                      <fills>
                        <FillStyle index="1">
                          <SolidColor color="#D0AA5A"/>
                        </FillStyle>
                      </fills>
                      <edges>
                        <Edge fillStyle1="1" edges="
!3663.5 769.5[#E4E.32 #315.EA 3661.5 797.5!3661.5 797.5[#E4C.E7 #325.54 3654 857.5!3654 857.5[#E3E.F6 #38D.75 3631 946!3631 946[#E1F.0C #3D6.99 3617.5 1008!3617.5 1008[#E24.15 #409.34 3645.5 1126.5!3645.5 1126.5[#E56.AB #4C4.07 3664.5
 1291.5!3664.5 1291.5[#E4A.23 #553.0A 3656 1416.5!3656 1416.5[#E46.04 #5BD.F2 3651 1576!3651 1576[#E3F.EB #692.08 3604.5 1715!3604.5 1715[#DE9.08 #6D3.FE 3522 1752!3522 1752[#D98.C7 #6DC.5 3446.5 1756!3446.5 1756[#D92.A4 #6DB.63 3507
 1752!3507 1752[3546 1748 3590 1715!3590 1715[3633 1682 3636 1576!3636 1576[3639 1470 3641 1417!3641 1417[3643 1363 3650 1292!3650 1292[3656 1220 3621 1088!3621 1088[3605 #406.1B 3606 999.5!3606 999.5[#E16.F1 #3C8.DA 3628.5 911!3628.5
 911[#E42.0F #355.33 3657.5 801!3657.5 801[#E50.FA #2EC.C1 3663.5 769.5"/>
                        <Edge cubics="!3522 1752(;3497,1755 3473,1756 3447,1756q3522 1752 3447 1756);"/>
                        <Edge cubics="!3656 1417(;3657,1381 3660,1339 3665,1292q3656 1417Q3658 1363q3665 1292);"/>
                        <Edge cubics="!3522 1752(;3548,1749 3576,1737 3605,1715q3522 1752Q3561 1748q3605 1715);"/>
                        <Edge cubics="!3605 1715(;3634,1693 3649,1647 3651,1576q3605 1715Q3648 1682q3651 1576);"/>
                        <Edge cubics="!3651 1576(;3653,1505 3655,1452 3656,1417q3651 1576Q3654 1470q3656 1417);"/>
                        <Edge cubics="!3507 1752(;3488,1754 3470,1755 3447,1756q3507 1752 3447 1756);"/>
                        <Edge cubics="!3650 1292(;3654,1244 3644,1176 3621,1088q3650 1292Q3656 1220q3621 1088);"/>
                        <Edge cubics="!3641 1417(;3642,1381 3645,1339 3650,1292q3641 1417Q3643 1363q3650 1292);"/>
                        <Edge cubics="!3507 1752(;3533,1749 3561,1737 3590,1715q3507 1752Q3546 1748q3590 1715);"/>
                        <Edge cubics="!3590 1715(;3619,1693 3634,1647 3636,1576q3590 1715Q3633 1682q3636 1576);"/>
                        <Edge cubics="!3636 1576(;3638,1505 3640,1452 3641,1417q3636 1576Q3639 1470q3641 1417);"/>
                        <Edge cubics="!3658 801(;3663,766 3665,756 3664,770q3658 801Q3665 749q3664 770);"/>
                        <Edge cubics="!3629 911(;3643,872 3653,836 3658,801q3629 911Q3650 853q3658 801);"/>
                        <Edge cubics="!3654 858(;3649,892 3642,921 3631,946q3654 858Q3647 909q3631 946);"/>
                        <Edge cubics="!3662 798(;3661,803 3659,823 3654,858q3662 798Q3661 805q3654 858);"/>
                        <Edge cubics="!3664 770(;3663,783 3662,793 3662,798q3664 770Q3662 790q3662 798);"/>
                        <Edge cubics="!3646 1127(;3663,1189 3669,1244 3665,1292q3646 1127Q3671 1220q3665 1292);"/>
                        <Edge cubics="!3621 1088(;3610,1049 3605,1020 3606,1000q3621 1088Q3605 1030q3606 1000);"/>
                        <Edge cubics="!3618 1008(;3619,1025 3629,1064 3646,1127q3618 1008Q3620 1033q3646 1127);"/>
                        <Edge cubics="!3606 1000(;3607,979 3614,950 3629,911q3606 1000Q3607 969q3629 911);"/>
                        <Edge cubics="!3631 946(;3620,971 3616,991 3618,1008q3631 946Q3615 983q3618 1008);"/>
                      </edges>
                    </DOMShape>
                  </members>
                </DOMGroup>
                <DOMGroup selected="true">
                  <members>
                    <DOMShape isDrawingObject="true">
                      <matrix>
                        <Matrix tx="-223.6" ty="101.25"/>
                      </matrix>
                      <fills>
                        <FillStyle index="1">
                          <SolidColor color="#D0AA5A"/>
                        </FillStyle>
                      </fills>
                      <edges>
                        <Edge fillStyle1="1" edges="
!5353 -1135[5376 -1176 5425 -1169!5425 -1169[5481 -1161 5533 -1091!5533 -1091[5713 -821 5539 -746!5539 -746[5420 -725 5388 -856!5388 -856[5383 -877 5370 -917!5370 -917[5357 -958 5335 -1009!5335 -1009[5312 -1061 5353 -1135"/>
                        <Edge cubics="!5539 -746(;5460,-732 5409,-769 5388,-856q5539 -746Q5420 -725q5388 -856);"/>
                        <Edge cubics="!5370 -917(;5361,-944 5350,-975 5335,-1009q5370 -917Q5353 -969q5335 -1009);"/>
                        <Edge cubics="!5388 -856(;5385,-870 5379,-890 5370,-917q5388 -856Q5384 -876q5370 -917);"/>
                        <Edge cubics="!5353 -1135(;5380,-1184 5458,-1191 5533,-1091q5353 -1135Q5376 -1176q5425 -1169Q5481 -1161q5533 -1091);"/>
                        <Edge cubics="!5335 -1009(;5320,-1044 5326,-1086 5353,-1135q5335 -1009Q5312 -1061q5353 -1135);"/>
                        <Edge cubics="!5533 -1091(;5653,-911 5655,-796 5539,-746q5533 -1091Q5713 -821q5539 -746);"/>
                      </edges>
                    </DOMShape>
                    <DOMGroup>
                      <members>
                        <DOMShape>
                          <fills>
                            <FillStyle index="1">
                              <SolidColor alpha="0.450980392156863"/>
                            </FillStyle>
                            <FillStyle index="2">
                              <SolidColor alpha="0.298039215686275"/>
                            </FillStyle>
                            <FillStyle index="3">
                              <SolidColor alpha="0.105882352941176"/>
                            </FillStyle>
                            <FillStyle index="4">
                              <SolidColor alpha="0.6"/>
                            </FillStyle>
                          </fills>
                          <edges>
                            <Edge fillStyle0="3" fillStyle1="2" edges="
!991 911[904 906 920 960!920 960[935 1014 970 1024!970 1024[1005 1033 990 1004!990 1004[975 974 944 965"/>
                            <Edge fillStyle0="3" fillStyle1="1" edges="
!944 965[965 956 982 956!982 956[1004 955 1021 967"/>
                            <Edge fillStyle0="3" edges="
!1021 967[998 933 1037 934!1037 934[1022 925 1009 919!1009 919[999 914 991 911"/>
                            <Edge fillStyle1="2" edges="
!904 949[904 941 905 934!905 934[913 878 991 911"/>
                            <Edge fillStyle1="1" edges="
!981 1080[921 1066 907 975!907 975[904 961 904 949"/>
                            <Edge fillStyle1="4" edges="
!1069 1082[1071 1105 1072 1133!1072 1133[1027 1146 1026 1189"/>
                            <Edge fillStyle1="2" edges="
!1026 1189[1025 1199 1027 1211"/>
                            <Edge fillStyle1="3" edges="
!1027 1211[1016 1243 990 1211"/>
                            <Edge fillStyle1="2" edges="
!990 1211[992 1196 993 1183"/>
                            <Edge fillStyle1="1" edges="
!993 1183[993 1132 954 1120!954 1120[925 1107 973 1104"/>
                            <Edge fillStyle1="3" edges="
!973 1104[999 1095 981 1080"/>
                            <Edge fillStyle0="1" fillStyle1="4" edges="
!1026 1189[977 1136 1018 1130!1018 1130[1059 1122 1069 1082"/>
                            <Edge fillStyle0="1" edges="
!1069 1082[1058 993 1021 967"/>
                            <Edge fillStyle0="1" fillStyle1="2" edges="
!1018 1081[1027 1079 1037 1077!1037 1077[1076 1085 1024 1119!1024 1119[992 1139 1004 1102"/>
                            <Edge fillStyle0="1" fillStyle1="3" edges="
!1004 1102[986 1102 973 1104"/>
                            <Edge fillStyle0="1" fillStyle1="2" edges="
!944 965[998 958 1031 990!1031 990[1064 1021 1032 1056!1032 1056[999 1090 958 1060!958 1060[917 1030 904 949"/>
                            <Edge fillStyle0="3" fillStyle1="2" edges="
!1027 1211[1010 1172 990 1211"/>
                            <Edge fillStyle0="1" fillStyle1="2" edges="
!993 1183[999 1172 1026 1189"/>
                            <Edge fillStyle0="3" fillStyle1="2" edges="
!1004 1102[1030 1093 1018 1081"/>
                            <Edge fillStyle0="3" fillStyle1="1" edges="
!1018 1081[997 1083 981 1080"/>
                            <Edge cubics="!1009 919(;1018,923 1027,928 1037,934q1009 919 1037 934);"/>
                            <Edge cubics="!982 956(;971,956 958,959 944,965q982 956Q965 956q944 965);"/>
                            <Edge cubics="!1021 967(;1010,959 997,955 982,956q1021 967Q1004 955q982 956);"/>
                            <Edge cubics="!1072 1133(;1071,1114 1070,1097 1069,1082q1072 1133 1069 1082);"/>
                            <Edge cubics="!1037 1077(;1063,1082 1059,1096 1024,1119q1037 1077Q1076 1085q1024 1119);"/>
                            <Edge cubics="!1018 1081(;1024,1080 1030,1078 1037,1077q1018 1081 1037 1077);"/>
                            <Edge cubics="!973 1104(;990,1098 993,1090 981,1080q973 1104Q999 1095q981 1080);"/>
                            <Edge cubics="!973 1104(;982,1103 992,1102 1004,1102q973 1104Q991 1102q1004 1102);"/>
                            <Edge cubics="!990 1211(;991,1201 992,1192 993,1183q990 1211 993 1183);"/>
                            <Edge cubics="!1026 1189(;1025,1196 1026,1203 1027,1211q1026 1189Q1025 1196q1027 1211);"/>
                            <Edge cubics="!993 1183(;993,1149 980,1128 954,1120q993 1183Q993 1132q954 1120);"/>
                            <Edge cubics="!981 1080(;992,1082 1004,1082 1018,1081q981 1080Q995 1083q1018 1081);"/>
                            <Edge cubics="!1004 1102(;1021,1096 1026,1089 1018,1081q1004 1102Q1030 1093q1018 1081);"/>
                            <Edge cubics="!1027 1211(;1020,1232 1007,1232 990,1211q1027 1211Q1016 1243q990 1211);"/>
                            <Edge cubics="!1004 1102(;996,1127 1003,1132 1024,1119q1004 1102Q992 1139q1024 1119);"/>
                            <Edge cubics="!907 975(;916,1036 941,1071 981,1080q907 975Q921 1066q981 1080);"/>
                            <Edge cubics="!907 975(;905,966 904,957 904,949q907 975 904 949);"/>
                            <Edge cubics="!1032 1056(;1010,1079 985,1080 958,1060q1032 1056Q999 1090q958 1060);"/>
                            <Edge cubics="!1031 990(;1053,1011 1053,1033 1032,1056q1031 990Q1064 1021q1032 1056);"/>
                            <Edge cubics="!904 949(;904,944 904,939 905,934q904 949Q904 941q905 934);"/>
                            <Edge cubics="!1009 919(;1002,916 996,913 991,911q1009 919Q999 914q991 911);"/>
                            <Edge cubics="!1021 967(;1006,944 1011,933 1037,934q1021 967Q998 933q1037 934);"/>
                            <Edge cubics="!970 1024(;993,1030 1000,1023 990,1004q970 1024Q1005 1033q990 1004);"/>
                            <Edge cubics="!905 934(;910,897 939,889 991,911q905 934Q913 878q991 911);"/>
                            <Edge cubics="!944 965(;980,960 1009,969 1031,990q944 965Q998 958q1031 990);"/>
                            <Edge cubics="!990 1004(;980,984 965,971 944,965q990 1004Q975 974q944 965);"/>
                            <Edge cubics="!920 960(;930,996 947,1017 970,1024q920 960Q935 1014q970 1024);"/>
                            <Edge cubics="!991 911(;933,908 909,924 920,960q991 911Q904 906q920 960);"/>
                            <Edge cubics="!993 1183(;997,1176 1008,1178 1026,1189q993 1183Q999 1172q1026 1189);"/>
                            <Edge cubics="!1027 1211(;1016,1185 1003,1185 990,1211q1027 1211Q1010 1172q990 1211);"/>
                            <Edge cubics="!1026 1189(;1027,1160 1042,1142 1072,1133q1026 1189Q1027 1146q1072 1133);"/>
                            <Edge cubics="!1026 1189(;993,1154 991,1134 1018,1130q1026 1189Q977 1136q1018 1130);"/>
                            <Edge cubics="!1018 1130(;1045,1125 1062,1109 1069,1082q1018 1130Q1059 1122q1069 1082);"/>
                            <Edge cubics="!973 1104(;941,1106 935,1111 954,1120q973 1104Q925 1107q954 1120);"/>
                            <Edge cubics="!958 1060(;931,1040 913,1003 904,949q958 1060Q917 1030q904 949);"/>
                            <Edge cubics="!1069 1082(;1062,1023 1046,984 1021,967q1069 1082Q1058 993q1021 967);"/>
                          </edges>
                        </DOMShape>
                      </members>
                    </DOMGroup>
                  </members>
                </DOMGroup>
                <DOMGroup selected="true">
                  <members>
                    <DOMShape selected="true">
                      <fills>
                        <FillStyle index="1">
                          <SolidColor color="#4E1A10"/>
                        </FillStyle>
                      </fills>
                      <edges>
                        <Edge fillStyle0="1" edges="
!1252 905S1[1224 510 1592 347!1592 347[1665 182 1350 62!1350 62[1034 -59 705 55!705 55[375 168 271 564!271 564[166 960 0 979!0 979[95 1037 246 976!246 976[226 1048 135 1094!135 1094[247 1128 302 1090!302 1090[302 1157 240 1200!240 1200
[297 1212 340 1175!340 1175[349 1228 299 1265!299 1265[339 1284 387 1265!387 1265[391 1288 365 1310!365 1310[590 1287 615 1448!615 1448[634 1573 652 1590!652 1590[818 1683 965 1257!965 1257[927 1230 911 1164!911 1164[906 1143 893 1103
!893 1103[880 1062 858 1011!858 1011[835 959 876 885!876 885[899 844 948 851!948 851[1004 859 1056 929!1056 929[1074 1100 1288 1097!1288 1097[1158 1024 1200 837!1200 837[1216 889 1252 905"/>
                        <Edge cubics="!240 1200(;278,1208 311,1200 340,1175q240 1200Q297 1212q340 1175);"/>
                        <Edge cubics="!299 1265(;326,1278 355,1278 387,1265q299 1265Q339 1284q387 1265);"/>
                        <Edge cubics="!1592 347(;1641,237 1560,142 1350,62q1592 347Q1665 182q1350 62);"/>
                        <Edge cubics="!1252 905(;1228,894 1211,872 1200,837q1252 905Q1216 889q1200 837);"/>
                        <Edge cubics="!948 851(;985,856 1021,882 1056,929q948 851Q1004 859q1056 929);"/>
                        <Edge cubics="!1056 929(;1068,1043 1145,1099 1288,1097q1056 929Q1074 1100q1288 1097);"/>
                        <Edge cubics="!1288 1097(;1201,1048 1172,962 1200,837q1288 1097Q1158 1024q1200 837);"/>
                        <Edge cubics="!705 55(;485,130 340,300 271,564q705 55Q375 168q271 564);"/>
                        <Edge cubics="!893 1103(;884,1076 873,1045 858,1011q893 1103Q876 1051q858 1011);"/>
                        <Edge cubics="!271 564(;201,828 111,966 0,979q271 564Q166 960q0 979);"/>
                        <Edge cubics="!876 885(;891,858 915,846 948,851q876 885Q899 844q948 851);"/>
                        <Edge cubics="!911 1164(;908,1150 902,1130 893,1103q911 1164Q907 1144q893 1103);"/>
                        <Edge cubics="!652 1590(;763,1652 867,1541 965,1257q652 1590Q818 1683q965 1257);"/>
                        <Edge cubics="!1350 62(;1139,-19 924,-21 705,55q1350 62Q1034 -59q705 55);"/>
                        <Edge cubics="!965 1257(;940,1239 922,1208 911,1164q965 1257Q927 1230q911 1164);"/>
                        <Edge cubics="!1252 905(;1233,642 1347,456 1592,347q1252 905Q1224 510q1592 347);"/>
                        <Edge cubics="!858 1011(;843,976 849,934 876,885q858 1011Q835 959q876 885);"/>
                        <Edge cubics="!246 976(;233,1024 196,1063 135,1094q246 976Q226 1048q135 1094);"/>
                        <Edge cubics="!135 1094(;210,1117 265,1115 302,1090q135 1094Q247 1128q302 1090);"/>
                        <Edge cubics="!302 1090(;302,1135 281,1171 240,1200q302 1090Q302 1157q240 1200);"/>
                        <Edge cubics="!340 1175(;346,1210 332,1240 299,1265q340 1175Q349 1228q299 1265);"/>
                        <Edge cubics="!615 1448(;628,1531 640,1579 652,1590q615 1448Q634 1573q652 1590);"/>
                        <Edge cubics="!387 1265(;390,1280 382,1295 365,1310q387 1265Q391 1288q365 1310);"/>
                        <Edge cubics="!365 1310(;515,1295 598,1341 615,1448q365 1310Q590 1287q615 1448);"/>
                        <Edge cubics="!0 979(;63,1018 145,1017 246,976q0 979Q95 1037q246 976);"/>
                      </edges>
                    </DOMShape>
                    <DOMGroup>
                      <members>
                        <DOMShape>
                          <fills>
                            <FillStyle index="1">
                              <SolidColor color="#FFFFFF" alpha="0.2"/>
                            </FillStyle>
                          </fills>
                          <edges>
                            <Edge fillStyle0="1" edges="
!412 612[454 734 369 916!369 916[563 833 648 698!648 698[573 772 414 872!414 872[497 647 395 535!395 535[353 795 116 952!116 952[358 845 412 612"/>
                          </edges>
                        </DOMShape>
                      </members>
                    </DOMGroup>
                    <DOMGroup>
                      <members>
                        <DOMShape>
                          <fills>
                            <FillStyle index="1">
                              <SolidColor color="#FFFFFF" alpha="0.2"/>
                            </FillStyle>
                          </fills>
                          <edges>
                            <Edge fillStyle1="1" edges="
!998 496[991 398 1066 324!1066 324[940 331 839 400!839 400[898 215 1112 166!1112 166[911 108 678 133!678 133[1075 -70 1478 159!1478 159[1152 10 854 99!854 99[1062 79 1209 170!1209 170[1034 214 930 314!930 314[1032 284 1126 299!1126 299
[1029 365 998 496"/>
                          </edges>
                        </DOMShape>
                      </members>
                    </DOMGroup>
                    <DOMGroup>
                      <members>
                        <DOMShape>
                          <fills>
                            <FillStyle index="1">
                              <SolidColor alpha="0.298039215686275"/>
                            </FillStyle>
                          </fills>
                          <edges>
                            <Edge fillStyle0="1" edges="
!246 944[213 996 0 979!0 979[95 1037 246 976!246 976[251 958 246 944!681 958[716 954 728 927!728 927[742 1017 618 1051!618 1051[640 1020 618 988!618 988[589 1052 487 1059!487 1059[518 1003 487 947!487 947[443 1026 348 1040!348 1040[367
 1006 348 971!348 971[333 1026 288 1056!288 1056[233 1092 135 1094!135 1094[247 1128 302 1090!302 1090[314 1084 328 1066!328 1066[389 1066 447 1038!447 1038[403 1104 338 1116!338 1116[408 1148 478 1116!478 1116[424 1168 328 1141!328 1141
[319 1179 240 1200!240 1200[297 1212 340 1175!340 1175[343 1192 340 1207!340 1207[352 1209 364 1192!364 1192[364 1254 299 1265!299 1265[339 1284 387 1265!387 1265[391 1288 365 1310!365 1310[590 1287 615 1448!615 1448[634 1573 652 1590
!652 1590[818 1683 965 1257!965 1257[927 1230 911 1164!911 1164[906 1143 893 1103!893 1103[880 1062 858 1011!858 1011[845 981 852 945!852 945[823 991 784 998!784 998[812 931 757 848!757 848[734 906 681 958"/>
                          </edges>
                        </DOMShape>
                      </members>
                    </DOMGroup>
                  </members>
                </DOMGroup>
                <DOMGroup selected="true">
                  <members>
                    <DOMShape selected="true">
                      <fills>
                        <FillStyle index="1">
                          <SolidColor color="#4E1A10"/>
                        </FillStyle>
                      </fills>
                      <edges>
                        <Edge fillStyle0="1" edges="
!1536 751S1[1446 768 1427 775!1427 775[1364 799 1362 819!1362 819[1385 796 1462 781!1462 781[1531 767 1544 772!1544 772[1558 777 1581 800!1581 800[1601 820 1609 820!1609 820[1635 820 1616 795!1616 795[1606 783 1583 767!1583 767[1554 748
 1536 751"/>
                        <Edge cubics="!1362 819(;1377,804 1411,791 1462,781q1362 819Q1385 796q1462 781);"/>
                        <Edge cubics="!1427 775(;1385,791 1363,806 1362,819q1427 775Q1364 799q1362 819);"/>
                        <Edge cubics="!1544 772(;1553,775 1566,785 1581,800q1544 772Q1558 777q1581 800);"/>
                        <Edge cubics="!1581 800(;1594,813 1604,820 1609,820q1581 800Q1601 820q1609 820);"/>
                        <Edge cubics="!1609 820(;1626,820 1629,812 1616,795q1609 820Q1635 820q1616 795);"/>
                        <Edge cubics="!1616 795(;1609,787 1598,778 1583,767q1616 795Q1606 783q1583 767);"/>
                        <Edge cubics="!1583 767(;1564,754 1548,749 1536,751q1583 767Q1554 748q1536 751);"/>
                        <Edge cubics="!1462 781(;1508,772 1535,769 1544,772q1462 781Q1531 767q1544 772);"/>
                        <Edge cubics="!1536 751(;1476,762 1440,770 1427,775q1536 751Q1446 768q1427 775);"/>
                      </edges>
                    </DOMShape>
                  </members>
                </DOMGroup>
                <DOMShape selected="true" isDrawingObject="true">
                  <matrix>
                    <Matrix tx="-98.6"/>
                  </matrix>
                  <fills>
                    <FillStyle index="1">
                      <SolidColor color="#D3B368"/>
                    </FillStyle>
                  </fills>
                  <edges>
                    <Edge fillStyle0="1" edges="
!3691 1431[#E44.B1 #556.A9 3631.5 1322.5!3631.5 1322.5[#E1A.82 #4FE.2C 3568.5 1378!3568.5 1378[#DC6.3A #5C6.0D 3548 1577.5!3548 1577.5[#DE1.D7 #643.EA 3556 1617!3556 1617[#E13.37 #695.9 3626 1628.5!3626 1628.5[#E44.B1 #619.A7 3676 1567
!3676 1567[3690 1546 3689 1530!3689 1530[3688 1507 3645 1497!3645 1497[3686 1488 3696 1464!3696 1464[3703 1445 3691 1431"/>
                    <Edge cubics="!3691 1431(;3699,1440 3701,1451 3696,1464q3691 1431Q3703 1445q3696 1464);"/>
                    <Edge cubics="!3696 1464(;3689,1480 3672,1491 3645,1497q3696 1464Q3686 1488q3645 1497);"/>
                    <Edge cubics="!3645 1497(;3674,1504 3688,1515 3689,1530q3645 1497Q3688 1507q3689 1530);"/>
                    <Edge cubics="!3676 1567(;3685,1553 3690,1541 3689,1530q3676 1567Q3690 1546q3689 1530);"/>
                    <Edge cubics="!3632 1323(;3618,1293 3597,1311 3569,1378q3632 1323Q3611 1278q3569 1378);"/>
                    <Edge cubics="!3548 1578(;3552,1595 3555,1608 3556,1617q3548 1578Q3554 1604q3556 1617);"/>
                    <Edge cubics="!3556 1617(;3587,1663 3611,1667 3626,1629q3556 1617Q3603 1686q3626 1629);"/>
                    <Edge cubics="!3691 1431(;3666,1388 3646,1352 3632,1323q3691 1431Q3653 1367q3632 1323);"/>
                    <Edge cubics="!3569 1378(;3540,1445 3533,1511 3548,1578q3569 1378Q3526 1478q3548 1578);"/>
                    <Edge cubics="!3626 1629(;3644,1584 3661,1564 3676,1567q3626 1629Q3653 1562q3676 1567);"/>
                  </edges>
                </DOMShape>
                <DOMShape selected="true" isDrawingObject="true">
                  <matrix>
                    <Matrix tx="-98.6"/>
                  </matrix>
                  <fills>
                    <FillStyle index="1">
                      <SolidColor color="#D3B368"/>
                    </FillStyle>
                  </fills>
                  <edges>
                    <Edge fillStyle1="1" edges="
!3634 824[3629 899 3634 956!3634 956[3640 1022 3656 1053!3656 1053[3703 1143 3750 1188!3750 1188[3796 1232 3789 1266!3789 1266[3782 1300 3748 1316!3748 1316[3739 1321 3695 1330!3695 1330[3645 1340 3615 1340!3615 1340[3586 1340 3583 1301
!3583 1301[3579 1261 3617 1243!3617 1243[3538 1210 3547 1032!3547 1032[3550 962 3569 920!3569 920[3590 874 3634 824"/>
                    <Edge cubics="!3789 1266(;3784,1289 3771,1305 3748,1316q3789 1266Q3782 1300q3748 1316);"/>
                    <Edge cubics="!3750 1188(;3781,1217 3794,1243 3789,1266q3750 1188Q3796 1232q3789 1266);"/>
                    <Edge cubics="!3656 1053(;3687,1113 3719,1158 3750,1188q3656 1053Q3703 1143q3750 1188);"/>
                    <Edge cubics="!3748 1316(;3740,1320 3660,1340 3615,1340q3748 1316Q3739 1321q3695 1330Q3645 1340q3615 1340);"/>
                    <Edge cubics="!3617 1243(;3563,1268 3580,1340 3615,1340q3617 1243Q3579 1261q3583 1301Q3586 1340q3615 1340);"/>
                    <Edge cubics="!3569 920(;3583,889 3605,857 3634,824q3569 920Q3590 874q3634 824);"/>
                    <Edge cubics="!3634 824(;3631,874 3631,918 3634,956q3634 824Q3629 899q3634 956);"/>
                    <Edge cubics="!3617 1243(;3564,1221 3541,1151 3547,1032q3617 1243Q3538 1210q3547 1032);"/>
                    <Edge cubics="!3547 1032(;3549,985 3556,948 3569,920q3547 1032Q3550 962q3569 920);"/>
                    <Edge cubics="!3634 956(;3638,1000 3645,1032 3656,1053q3634 956Q3640 1022q3656 1053);"/>
                  </edges>
                </DOMShape>
                <DOMGroup selected="true">
                  <members>
                    <DOMShape isDrawingObject="true">
                      <matrix>
                        <Matrix tx="-98.6"/>
                      </matrix>
                      <fills>
                        <FillStyle index="1">
                          <LinearGradient>
                            <matrix>
                              <Matrix a="-0.0005340576171875" b="0.0020294189453125" c="-0.004608154296875" d="-0.001190185546875" tx="180.65" ty="76.15"/>
                            </matrix>
                            <GradientEntry color="#4A0202" alpha="0.498039215686275" ratio="0"/>
                            <GradientEntry color="#B10101" alpha="0.309803921568627" ratio="1"/>
                          </LinearGradient>
                        </FillStyle>
                      </fills>
                      <edges>
                        <Edge fillStyle1="1" edges="
!3603 1501[3624 1495 3645 1497!3645 1497[3688 1507 3689 1530!3689 1530[3690 1546 3676 1567!3676 1567[3617 1577 3536 1508!3536 1508[3566 1515 3603 1501"/>
                        <Edge cubics="!3645 1497(;3631,1496 3617,1497 3603,1501q3645 1497Q3623 1495q3603 1501);"/>
                        <Edge cubics="!3645 1497(;3674,1504 3688,1515 3689,1530q3645 1497Q3688 1507q3689 1530);"/>
                        <Edge cubics="!3536 1508(;3556,1513 3578,1510 3603,1501q3536 1508Q3566 1515q3603 1501);"/>
                        <Edge cubics="!3676 1567(;3685,1553 3690,1541 3689,1530q3676 1567Q3690 1546q3689 1530);"/>
                        <Edge cubics="!3536 1508(;3590,1554 3637,1574 3676,1567q3536 1508Q3617 1577q3676 1567);"/>
                      </edges>
                    </DOMShape>
                    <DOMShape isDrawingObject="true">
                      <matrix>
                        <Matrix tx="-98.6"/>
                      </matrix>
                      <fills>
                        <FillStyle index="1">
                          <LinearGradient>
                            <matrix>
                              <Matrix a="-0.0005035400390625" b="-0.00189208984375" c="0.00506591796875" d="-0.0013427734375" tx="180.8" ty="73.6"/>
                            </matrix>
                            <GradientEntry color="#4A0202" alpha="0.498039215686275" ratio="0"/>
                            <GradientEntry color="#B10101" alpha="0.309803921568627" ratio="1"/>
                          </LinearGradient>
                        </FillStyle>
                      </fills>
                      <edges>
                        <Edge fillStyle0="1" edges="
!3672 1425[3653 1427 3618 1456!3618 1456[3574 1492 3536 1508!3536 1508[3566 1515 3603 1501!3603 1501[3624 1495 3645 1497!3645 1497[3686 1488 3696 1464!3696 1464[3703 1445 3691 1431!3691 1431[3680 1424 3672 1425"/>
                        <Edge cubics="!3645 1497(;3631,1496 3617,1497 3603,1501q3645 1497Q3623 1495q3603 1501);"/>
                        <Edge cubics="!3691 1431(;3699,1440 3701,1451 3696,1464q3691 1431Q3703 1445q3696 1464);"/>
                        <Edge cubics="!3696 1464(;3689,1480 3672,1491 3645,1497q3696 1464Q3686 1488q3645 1497);"/>
                        <Edge cubics="!3672 1425(;3664,1426 3647,1432 3618,1456q3672 1425Q3653 1427q3618 1456);"/>
                        <Edge cubics="!3691 1431(;3684,1426 3677,1424 3672,1425q3691 1431Q3680 1424q3672 1425);"/>
                        <Edge cubics="!3618 1456(;3589,1480 3561,1497 3536,1508q3618 1456Q3574 1492q3536 1508);"/>
                        <Edge cubics="!3536 1508(;3556,1513 3578,1510 3603,1501q3536 1508Q3566 1515q3603 1501);"/>
                      </edges>
                    </DOMShape>
                  </members>
                </DOMGroup>
                <DOMGroup selected="true">
                  <members>
                    <DOMGroup selected="true">
                      <members>
                        <DOMShape selected="true">
                          <fills>
                            <FillStyle index="1">
                              <SolidColor/>
                            </FillStyle>
                            <FillStyle index="2">
                              <SolidColor color="#FFFFFF"/>
                            </FillStyle>
                          </fills>
                          <edges>
                            <Edge fillStyle0="1" edges="
!1549 902S1[1572 892 1573 874!1573 874[1563 888 1551 888!1551 888[1562 873 1556 863!1556 863[1551 881 1522 899!1522 899[1527 892 1521 879!1521 879[1507 899 1486 918!1486 918[1464 937 1453 953!1453 953[1441 968 1424 981"/>
                            <Edge fillStyle0="1" fillStyle1="2" edges="
!1424 981S3[1442 973 1460 957!1460 957[1501 915 1549 902"/>
                            <Edge fillStyle0="1" edges="
!1448 996S1[1492 1029 1564 1028!1564 1028[1548 1024 1542 1015"/>
                            <Edge fillStyle0="1" fillStyle1="2" edges="
!1542 1015S3[1486 1015 1448 996"/>
                            <Edge fillStyle1="2" edges="
!1549 902S2[1562 953 1542 1015!1448 996[1435 990 1424 981"/>
                          </edges>
                        </DOMShape>
                      </members>
                    </DOMGroup>
                    <DOMSymbolInstance libraryItemName="skins/Perso1Skin_parts/iris" name="" selected="true" symbolType="graphic" loop="loop">
                      <matrix>
                        <Matrix a="0.0920257568359375" d="0.250869750976563" tx="77" ty="47.95"/>
                      </matrix>
                      <transformationPoint>
                        <Point/>
                      </transformationPoint>
                    </DOMSymbolInstance>
                    <DOMGroup selected="true">
                      <members>
                        <DOMShape selected="true">
                          <fills>
                            <FillStyle index="1">
                              <SolidColor color="#0099FF" alpha="0.298039215686275"/>
                            </FillStyle>
                          </fills>
                          <edges>
                            <Edge fillStyle1="1" edges="
!1460 957S2[1501 915 1549 902!1549 902[1562 953 1542 1015!1542 1015[1486 1015 1448 996!1448 996[1435 990 1424 981!1424 981[1442 973 1460 957"/>
                          </edges>
                        </DOMShape>
                      </members>
                    </DOMGroup>
                  </members>
                </DOMGroup>
                <DOMShape selected="true" isDrawingObject="true">
                  <matrix>
                    <Matrix tx="-98.6"/>
                  </matrix>
                  <fills>
                    <FillStyle index="1">
                      <SolidColor color="#D0AA5A"/>
                    </FillStyle>
                  </fills>
                  <edges>
                    <Edge fillStyle1="1" edges="
!3769 1291[#EE0.44 #4E7.D2 3761.5 1211!3761.5 1211[#E82.79 1166 3683.5 1118.5!3683.5 1118.5[#E44.E8 #42E.EC 3646.5 1038!3646.5 1038[#E37.CB #3ED.0F 3638 991.5!3638 991.5[#E3C.AD #407.1 3656 1053!3656 1053[3703 1143 3750 1188!3750 1188
[3796 1232 3789 1266!3789 1266[3782 1300 3748 1316!3748 1316[#E9A.EB #529.12 3697.5 1329.5!3697.5 1329.5[#E48.33 #539.C8 3631 1347!3631 1347[#E15.E1 #54C.31 3581.5 1323!3581.5 1323[#DE4.E9 #509.FC 3566 1247!3566 1247[3538 1210 3547 1032
!3547 1032[#DDB.2C #403.41 3548.5 1022.5!3548.5 1022.5[#DFF.0B #446.A3 3637 1185!3637 1185[#E6A.EF #4FB.92 3627 1279!3627 1279[#E25.78 #527.5 3675.5 1323!3675.5 1323[#E91.A1 #52E.74 3769 1291"/>
                    <Edge cubics="!3789 1266(;3784,1289 3771,1305 3748,1316q3789 1266Q3782 1300q3748 1316);"/>
                    <Edge cubics="!3750 1188(;3781,1217 3794,1243 3789,1266q3750 1188Q3796 1232q3789 1266);"/>
                    <Edge cubics="!3656 1053(;3687,1113 3719,1158 3750,1188q3656 1053Q3703 1143q3750 1188);"/>
                    <Edge cubics="!3638 992(;3644,1021 3649,1039 3656,1053q3638 992 3656 1053);"/>
                    <Edge cubics="!3547 1032(;3547,1031 3547,1030 3549,1023q3547 1032 3549 1023);"/>
                    <Edge cubics="!3549 1023(;3572,1071 3601,1125 3637,1185q3549 1023Q3583 1095q3637 1185);"/>
                    <Edge cubics="!3637 1185(;3673,1246 3670,1277 3627,1279q3637 1185Q3691 1276q3627 1279);"/>
                    <Edge cubics="!3676 1323(;3712,1325 3743,1314 3769,1291q3676 1323Q3730 1326q3769 1291);"/>
                    <Edge cubics="!3769 1291(;3795,1268 3793,1241 3762,1211q3769 1291Q3808 1256q3762 1211);"/>
                    <Edge cubics="!3762 1211(;3730,1181 3704,1150 3684,1119q3762 1211Q3714 1166q3684 1119);"/>
                    <Edge cubics="!3684 1119(;3663,1087 3651,1060 3647,1038q3684 1119Q3653 1071q3647 1038);"/>
                    <Edge cubics="!3627 1279(;3623,1306 3639,1320 3676,1323q3627 1279Q3621 1319q3676 1323);"/>
                    <Edge cubics="!3647 1038(;3642,1016 3639,1001 3638,992q3647 1038Q3640 1005q3638 992);"/>
                    <Edge cubics="!3748 1316(;3742,1319 3725,1324 3698,1330q3748 1316Q3739 1321q3698 1330);"/>
                    <Edge cubics="!3631 1347(;3614,1353 3598,1345 3582,1323q3631 1347Q3606 1356q3582 1323);"/>
                    <Edge cubics="!3698 1330(;3670,1335 3648,1341 3631,1347q3698 1330Q3656 1338q3631 1347);"/>
                    <Edge cubics="!3566 1247(;3547,1222 3541,1151 3547,1032q3566 1247Q3538 1210q3547 1032);"/>
                    <Edge cubics="!3582 1323(;3565,1301 3560,1276 3566,1247q3582 1323Q3557 1290q3566 1247);"/>
                  </edges>
                </DOMShape>
              </elements>
            </DOMFrame>
          </frames>
        </DOMLayer>
      </layers>
    </DOMTimeline>
  </timeline>
</DOMSymbolItem>